chartcrafthub/__init__.py
chartcrafthub/__main__.py
chartcrafthub/abstractions.py
chartcrafthub/anatomy_of_figure.py
chartcrafthub/chapter_1_0.ipynb
chartcrafthub/chapter_2_0.ipynb
chartcrafthub/chapter_2_1.ipynb
chartcrafthub/convay.py
chartcrafthub/convay_simplified.py
chartcrafthub/core.py
chartcrafthub/ex_1_1.py
chartcrafthub/ex_1_2.py
chartcrafthub/ex_2_1.py
chartcrafthub/ex_2_2.py
chartcrafthub/ex_2_3.py
chartcrafthub/ex_2_4.py
chartcrafthub/ex_2_5.py
chartcrafthub/ex_2_6.py
chartcrafthub/ex_2_7.py
chartcrafthub/index.html
chartcrafthub/index_pangram.html
chartcrafthub/logo_generator.ipynb
chartcrafthub/template.py
chartcrafthub/utils.py
chartcrafthub/fonts/RobotoMono-Regular.ttf
chartcrafthub/fonts/cmr10.ttf
chartcrafthub/results/common_chart_xkcd.png
chartcrafthub/results/ex_2_3.png
chartcrafthub/results/ex_2_4.png
chartcrafthub/results/ex_2_5.png
chartcrafthub/results/ex_2_6.png
chartcrafthub/results/ex_2_7.png
chartcrafthub/results/pangram.svg
chartcrafthub-1.0.2.dist-info/LICENSE
chartcrafthub-1.0.2.dist-info/METADATA
chartcrafthub-1.0.2.dist-info/WHEEL
chartcrafthub-1.0.2.dist-info/entry_points.txt
chartcrafthub-1.0.2.dist-info/top_level.txt
chartcrafthub-1.0.2.dist-info/RECORD
