Metadata-Version: 2.1
Name: chartcrafthub
Version: 1.0.2
Summary: Code, debug, reuse this chart, workshop materials and more.
Author-email: Artem Kislovskiy <artem.kislovskiy@gmail.com>, Teresa Kubacka <teresa@xurce.ch>
License: MIT License
Project-URL: Homepage, https://github.com/Kislovskiy/ChartCraftHub
Project-URL: Documenation, https://kislovskiy.github.io/ChartCraftHub/
Keywords: matplotlib,visuzlization,tutorial
Classifier: License :: OSI Approved :: MIT License
Classifier: Programming Language :: Python
Classifier: Programming Language :: Python :: 3
License-File: LICENSE
Requires-Dist: jupyter ==1.0.0
Requires-Dist: matplotlib ==3.8.3
Requires-Dist: numpy ==1.26.4
Requires-Dist: aquarel ==0.0.6
Requires-Dist: seaborn ==0.13.2
Requires-Dist: rich ==13.7.1
Provides-Extra: build
Requires-Dist: build ; extra == 'build'
Requires-Dist: twine ; extra == 'build'
Provides-Extra: dev
Requires-Dist: pytest ==8.0.2 ; extra == 'dev'
Requires-Dist: ruff ==0.3.4 ; extra == 'dev'
Requires-Dist: bumpver ==2023.1129 ; extra == 'dev'
Provides-Extra: docs
Requires-Dist: sphinx ==7.2.6 ; extra == 'docs'
Requires-Dist: furo ==2024.01.29 ; extra == 'docs'
